[
  {
    "PatientId": 2,
    "Rating": 3,
    "Message": "Voluptates corporis rerum pariatur porro consequatur.",
    "CreatedAt": "2024-10-02"
  },
  {
    "PatientId": 10,
    "Rating": 4,
    "Message": "Fugiat atque suscipit corrupti hic maxime aspernatur eligendi dolores exercitationem saepe.",
    "CreatedAt": "2025-04-03"
  },
  {
    "PatientId": 7,
    "Rating": 4,
    "Message": "Nihil perferendis dolor cumque asperiores ex atque necessitatibus nihil praesentium autem.",
    "CreatedAt": "2024-08-30"
  },
  {
    "PatientId": 5,
    "Rating": 4,
    "Message": "Eos excepturi possimus repellat sint laudantium iure eaque itaque natus illum.",
    "CreatedAt": "2024-12-26"
  },
  {
    "PatientId": 9,
    "Rating": 3,
    "Message": "Nisi ipsa culpa nihil culpa ratione omnis cupiditate exercitationem enim.",
    "CreatedAt": "2024-07-20"
  },
  {
    "PatientId": 10,
    "Rating": 4,
    "Message": "Natus voluptatum sint dolores officiis corrupti officia deserunt.",
    "CreatedAt": "2025-06-12"
  },
  {
    "PatientId": 5,
    "Rating": 3,
    "Message": "Soluta repellat error aliquam laudantium eum nulla totam perspiciatis optio sequi.",
    "CreatedAt": "2025-03-12"
  },
  {
    "PatientId": 10,
    "Rating": 4,
    "Message": "Nostrum rem hic nesciunt molestiae vero excepturi doloremque iure.",
    "CreatedAt": "2025-02-09"
  },
  {
    "PatientId": 1,
    "Rating": 3,
    "Message": "Nesciunt optio nobis cum exercitationem nihil aliquid eum quos impedit eos.",
    "CreatedAt": "2024-11-01"
  },
  {
    "PatientId": 5,
    "Rating": 4,
    "Message": "Nulla reiciendis aut a iste provident ea cupiditate eum.",
    "CreatedAt": "2025-01-14"
  }
]
